{
  "menu": [
    {
      "name": "Spaghetti Carbonara",
      "description": "Creamy pasta with bacon, eggs, and parmesan cheese.",
      "price": 12.99,
      "image_url": "https://example.com/menu/spaghetti_carbonara.jpg"
    },
    {
      "name": "Grilled Salmon",
      "description": "Fresh salmon fillet grilled to perfection.",
      "price": 16.99,
      "image_url": "https://example.com/menu/grilled_salmon.jpg"
    },
    {
      "name": "Margherita Pizza",
      "description": "Classic Italian pizza with tomato sauce, mozzarella, and basil.",
      "price": 10.99,
      "image_url": "https://example.com/menu/margherita_pizza.jpg"
    },
    {
      "name": "Caesar Salad",
      "description": "Crisp romaine lettuce, croutons, and parmesan cheese with Caesar dressing.",
      "price": 8.99,
      "image_url": "https://example.com/menu/caesar_salad.jpg"
    },
    {
      "name": "Chocolate Fondue",
      "description": "Melted chocolate served with fresh fruits and marshmallows for dipping.",
      "price": 9.99,
      "image_url": "https://example.com/menu/chocolate_fondue.jpg"
    }
  ]
}
